System_to_Matlab/__init__.py
System_to_Matlab/Calculation/Calculation.py
System_to_Matlab/Calculation/__init__.py
System_to_Matlab/FileGenerators/FileGenerators.py
System_to_Matlab/FileGenerators/MFile.py
System_to_Matlab/FileGenerators/MFunction.py
System_to_Matlab/FileGenerators/SFunction.py
System_to_Matlab/FileGenerators/__init__.py
System_to_Matlab/FileGenerators/MatlabElements/CodeElement.py
System_to_Matlab/FileGenerators/MatlabElements/MatlabElement.py
System_to_Matlab/FileGenerators/MatlabElements/StringElement.py
System_to_Matlab/FileGenerators/MatlabElements/__init__.py
System_to_Matlab/HelperFunctions/GeneralHelperFuncitons.py
System_to_Matlab/HelperFunctions/RobotikHelperFuncitons.py
System_to_Matlab/HelperFunctions/__init__.py
System_to_Matlab/Symbols/DynamicSymbol.py
System_to_Matlab/Symbols/StaticSymbol.py
System_to_Matlab/Symbols/Symbol.py
System_to_Matlab/Symbols/__init__.py
System_to_Matlab/Systems/DynamicSystem.py
System_to_Matlab/Systems/StaticSystem.py
System_to_Matlab/Systems/_System.py
System_to_Matlab/Systems/__init__.py
System_to_Matlab/tests/test_Calculation.py
System_to_Matlab/tests/test_CodeElement.py
System_to_Matlab/tests/test_DynamicSymbol.py
System_to_Matlab/tests/test_DynamicSystem.py
System_to_Matlab/tests/test_StaticSymbol.py
System_to_Matlab/tests/test_StaticSystem.py
System_to_Matlab/tests/test_StringElement.py
System_to_Matlab-0.0.5.dist-info/LICENSE
System_to_Matlab-0.0.5.dist-info/METADATA
System_to_Matlab-0.0.5.dist-info/WHEEL
System_to_Matlab-0.0.5.dist-info/top_level.txt
System_to_Matlab-0.0.5.dist-info/RECORD
