Metadata-Version: 2.1
Name: System_to_Matlab
Version: 0.0.5
Summary: With this package you can create Symbolic descriptions of Systems (Sympy / Symengine) and output them in Matlab files
Author: Martin Karlhuber
Requires-Python: >=3.7
License-File: LICENSE
Requires-Dist: sympy
Requires-Dist: symengine >=0.11.0
